adder.t.v
// Adder testbench
`timescale 1 ns / 1 ps
`include "adder.v"

module testFullAdder();
    reg addr0, addr1, carryin;
    wire sum, carryout;

    //behavioralFullAdder adder (sum, carryout, addr0, addr1, carryin);
    structuralFullAdder adder(sum, carryout, addr0, addr1, carryin);
    
    initial begin

    $dumpfile("adder.vcd");
    $dumpvars();

    $display("A B| CarryIn | CarryOut | Carry Out Should Be | Sum | Sum Should Be");

    addr0=0;addr1=0;carryin=0; #1000 
    $display("%b  %b | %b | %b | False | %b | False", addr0, addr1, carryin, carryout, sum );
    addr0=0;addr1=0;carryin=1; #1000 
    $display("%b  %b | %b | %b | False | %b | True", addr0, addr1, carryin, carryout, sum );

    addr0=0;addr1=1;carryin=0; #1000 
    $display("%b  %b | %b | %b | False | %b | True", addr0, addr1, carryin, carryout, sum );
    addr0=0;addr1=1;carryin=1; #1000 
    $display("%b  %b | %b | %b | True  | %b | False", addr0, addr1, carryin, carryout, sum );

    addr0=1;addr1=0;carryin=0; #1000 
    $display("%b  %b | %b | %b | False | %b | True", addr0, addr1, carryin, carryout, sum );
    addr0=1;addr1=0;carryin=1; #1000 
    $display("%b  %b | %b | %b | True  | %b | False", addr0, addr1, carryin, carryout, sum );

    addr0=1;addr1=1;carryin=0; #1000 
    $display("%b  %b | %b | %b | True  | %b | False", addr0, addr1, carryin, carryout, sum );
    addr0=1;addr1=1;carryin=1; #1000 
    $display("%b  %b | %b | %b | True  | %b | True", addr0, addr1, carryin, carryout, sum );

    $finish();

    end

endmodule

adder.v
// Adder circuit

`define AND and #50
`define OR or #50
`define NOT not #50
`define XOR xor #50

module behavioralFullAdder
(
    output sum, 
    output carryout,
    input a, 
    input b, 
    input carryin
);
    // Uses concatenation operator and built-in '+'
    assign {carryout, sum}=a+b+carryin;
endmodule

module structuralFullAdder
(
    output sum, 
    output carryout,
    input a, 
    input b, 
    input carryin

);

 wire AxorB, AxorBxorC, AxorBC, AB;

 `XOR xorGate(AxorB, a, b);
 `XOR xorGate(sum, AxorB, carryin);
 `AND andGate(AB, a, b);
 `AND andGate(AxorBC, carryin, AxorB);
 `OR orGate( carryout, AB, AxorBC);



endmodule

adder.vcd
$date
	Thu Sep 20 08:19:01 2018
$end
$version
	Icarus Verilog
$end
$timescale
	1ps
$end
$scope module behavioralFullAdder $end
$var wire 1 ! a $end
$var wire 1 " b $end
$var wire 1 # carryin $end
$var wire 1 $ sum $end
$var wire 1 % carryout $end
$upscope $end
$scope module testFullAdder $end
$var wire 1 & sum $end
$var wire 1 ' carryout $end
$var reg 1 ( addr0 $end
$var reg 1 ) addr1 $end
$var reg 1 * carryin $end
$scope module adder $end
$var wire 1 + AB $end
$var wire 1 , AxorB $end
$var wire 1 - AxorBC $end
$var wire 1 ( a $end
$var wire 1 ) b $end
$var wire 1 * carryin $end
$var wire 1 ' carryout $end
$var wire 1 & sum $end
$upscope $end
$upscope $end
$enddefinitions $end
#0
$dumpvars
x-
x,
x+
0*
0)
0(
x'
x&
x%
x$
z#
z"
z!
$end
#50000
0-
0+
0,
#100000
0'
0&
#1000000
1*
#1050000
1&
#2000000
0*
1)
#2050000
0&
1,
#2100000
1&
#3000000
1*
#3050000
0&
1-
#3100000
1'
#4000000
0*
0)
1(
#4050000
1&
0-
#4100000
0'
#5000000
1*
#5050000
0&
1-
#5100000
1'
#6000000
0*
1)
#6050000
1&
0-
0,
1+
#6100000
0&
#7000000
1*
#7050000
1&
